Lab3/Lab3_Mealy.v

module Lab3_Mealy(CLK, dataIn, RST, odd);
  // Input and Output Declarations
  input [3:0]  dataIn;
  input        CLK;
  input        RST;
  output       odd;

  // DataInternal Variables
  reg [3:0]  state;
  reg [3:0]  next_state;
  reg [4:0]  sumid;	

  // State Declarations (m?c dù state ch? dùng 3 bit, s? d?ng 4 bit cho nh?t quán)
  parameter reset = 3'b000;
  parameter s1    = 3'b001;
  parameter s2    = 3'b010;
  parameter s3    = 3'b011;

  // Combinational Next State Logic
  always @(*) begin
    case(state)
      reset: begin
        if (dataIn == 0) begin
          next_state = s1;
          sumid = sumid + dataIn;
        end
        else begin
          next_state = reset;
        end
      end
      s1: begin
        if (dataIn == 0) begin
          next_state = s2;
          sumid = sumid + dataIn;
        end
        else begin
          next_state = reset;
        end
      end
      s2: begin
        if (dataIn == 2) begin
          next_state = s3;
          sumid = sumid + dataIn;
        end
        else if (dataIn == 0) begin
          next_state = s2;
        end
        else begin
          next_state = reset;
        end
      end
      s3: begin
        if (dataIn == 5) begin
          next_state = reset;
          sumid = sumid + dataIn;
        end
        else if (dataIn == 0) begin
          next_state = s1;
        end
        else begin
          next_state = reset;
        end
      end
      default: begin
        next_state = reset;
      end
    endcase
  end

  // State FF Transition
  always @(posedge CLK) begin
    if (RST == 1)
      state <= reset;
    else
      state <= next_state;
  end

  // Combinational Output Logic
  assign odd = (state == s3 && dataIn == 5 && (sumid % 2 == 1)) ? 1 : 0;

endmodule // Mealy Student ID Detector

Lab3/Lab3_Mealy_tb.v
`timescale 1ns/1ps

module tb_Lab3_Mealy;
    reg        CLK;
    reg        RST;
    reg [3:0]  dataIn;
    wire       odd;

    // Instantiate the design under test with named ports
    Lab3_Mealy duttt (
        .CLK(CLK),
        .dataIn(dataIn),
        .RST(RST),
        .odd(odd)
    );

    // Waveform dump
    initial begin
        $dumpfile("Lab3_Mealy_tb.vcd");
        $dumpvars(0, tb_Lab3_Mealy);
    end

    // Clock generation: 10 ns period
    initial begin
        CLK = 0;
        forever #5 CLK = ~CLK;
    end

    // Task to drive a sequence of 4 digits.
    // The 16-bit input is structured as {digit0, digit1, digit2, digit3}
    // where digit0 is the first input.
    task drive_sequence;
        input [15:0] seq;
        integer i;
        reg [3:0] digit;
        begin
            // Apply each digit every 10 ns
            for(i = 3; i >= 0; i = i - 1) begin
                // Extract 4 bits per digit using bit slicing.
                digit = seq[(i*4) + 3 -: 4];
                dataIn = digit;
                #10;
            end
        end
    endtask

    initial begin
        // Initialization & reset
        RST = 1;
        dataIn = 4'd0;
        #10;
        RST = 0;
        #10;
        
        // Test Case 1: "0025" (Expected: sum = 0+0+2+5 = 7, odd=1)
        $display("Test Case 1: 0025");
        drive_sequence(16'h0025);
        #20;
        
        // Test Case 2: "1234"
        $display("Test Case 2: 1234");
        drive_sequence(16'h1234);
        #20;
        
        // Test Case 3: "0000"
        $display("Test Case 3: 0000");
        drive_sequence(16'h0000);
        #20;
        
        // Test Case 4: "0020" (Expected: 0+0+2+0 = 2, even => odd=0)
        $display("Test Case 4: 0020");
        drive_sequence(16'h0020);
        #20;
        
        // Test Case 5: "0027" (Sequence fails at last digit; output 0)
        $display("Test Case 5: 0027");
        drive_sequence(16'h0027);
        #20;
        
        // Test Case 6: "0500" (Invalid transition; output 0)
        $display("Test Case 6: 0500");
        drive_sequence(16'h0500);
        #20;
        
        // Test Case 7: "0215" (Invalid sequence; output 0)
        $display("Test Case 7: 0215");
        drive_sequence(16'h0215);
        #20;
        
        // Test Case 8: "0045" (Invalid at s2 transition; output 0)
        $display("Test Case 8: 0045");
        drive_sequence(16'h0045);
        #20;
        
        // Test Case 9: "0005" (Does not complete valid sequence; output 0)
        $display("Test Case 9: 0005");
        drive_sequence(16'h0005);
        #20;
        
        // Test Case 10: "1357" (Random sequence; output depends on FSM transitions)
        $display("Test Case 10: 1357");
        drive_sequence(16'h1357);
        #20;
        
        $finish;
    end

endmodule

Lab3/Lab3_Mealy_tb.vcd
$date
	Wed Apr 09 08:28:46 2025
$end
$version
	ModelSim Version 10.1d
$end
$timescale
	1ps
$end
$scope module tb_Lab3_Mealy $end
$var reg 1 ! CLK $end
$var reg 1 " RST $end
$var reg 4 # dataIn [3:0] $end
$var wire 1 $ odd $end
$scope task drive_sequence $end
$var reg 16 % seq [15:0] $end
$var integer 32 & i $end
$var reg 4 ' digit [3:0] $end
$upscope $end
$scope module duttt $end
$var parameter 3 ( reset $end
$var parameter 3 ) s1 $end
$var parameter 3 * s2 $end
$var parameter 3 + s3 $end
$var wire 1 , dataIn [3] $end
$var wire 1 - dataIn [2] $end
$var wire 1 . dataIn [1] $end
$var wire 1 / dataIn [0] $end
$var wire 1 0 CLK $end
$var wire 1 1 RST $end
$var wire 1 $ odd $end
$var reg 4 2 state [3:0] $end
$var reg 4 3 next_state [3:0] $end
$var reg 5 4 sumid [4:0] $end
$upscope $end
$upscope $end
$enddefinitions $end
#0
$dumpvars
0!
1"
b0 #
bx 2
b0 3
bx 4
bx %
bx '
b0 (
b1 )
b10 *
b11 +
bx &
0$
11
0/
0.
0-
0,
00
$end
#5000
1!
10
b0 2
b1 3
#10000
0"
0!
01
00
#15000
1!
10
b1 2
b10 3
#20000
b100101 %
b11 &
b0 '
0!
00
#25000
1!
10
b10 2
#30000
b10 &
0!
00
#35000
1!
10
#40000
b1 &
b10 '
b10 #
0!
1.
00
b11 3
#45000
1!
10
b11 2
b0 3
#50000
b0 &
b101 '
b101 #
0!
1/
0.
1-
00
x$
#55000
1!
10
b0 2
0$
#60000
b11111111111111111111111111111111 &
0!
00
#65000
1!
10
#70000
0!
00
#75000
1!
10
#80000
b1001000110100 %
b11 &
b1 '
b1 #
0!
0-
00
#85000
1!
10
#90000
b10 &
b10 '
b10 #
0!
0/
1.
00
#95000
1!
10
#100000
b1 &
b11 '
b11 #
0!
1/
00
#105000
1!
10
#110000
b0 &
b100 '
b100 #
0!
0/
0.
1-
00
#115000
1!
10
#120000
b11111111111111111111111111111111 &
0!
00
#125000
1!
10
#130000
0!
00
#135000
1!
10
#140000
b0 %
b11 &
b0 '
b0 #
0!
0-
00
b1 3
#145000
1!
10
b1 2
b10 3
#150000
b10 &
0!
00
#155000
1!
10
b10 2
#160000
b1 &
0!
00
#165000
1!
10
#170000
b0 &
0!
00
#175000
1!
10
#180000
b11111111111111111111111111111111 &
0!
00
#185000
1!
10
#190000
0!
00
#195000
1!
10
#200000
b100000 %
b11 &
0!
00
#205000
1!
10
#210000
b10 &
0!
00
#215000
1!
10
#220000
b1 &
b10 '
b10 #
0!
1.
00
b11 3
#225000
1!
10
b11 2
b0 3
#230000
b0 &
b0 '
b0 #
0!
0.
00
b1 3
#235000
1!
10
b1 2
b10 3
#240000
b11111111111111111111111111111111 &
0!
00
#245000
1!
10
b10 2
#250000
0!
00
#255000
1!
10
#260000
b100111 %
b11 &
0!
00
#265000
1!
10
#270000
b10 &
0!
00
#275000
1!
10
#280000
b1 &
b10 '
b10 #
0!
1.
00
b11 3
#285000
1!
10
b11 2
b0 3
#290000
b0 &
b111 '
b111 #
0!
1/
1-
00
#295000
1!
10
b0 2
#300000
b11111111111111111111111111111111 &
0!
00
#305000
1!
10
#310000
0!
00
#315000
1!
10
#320000
b10100000000 %
b11 &
b0 '
b0 #
0!
0/
0.
0-
00
b1 3
#325000
1!
10
b1 2
b10 3
#330000
b10 &
b101 '
b101 #
0!
1/
1-
00
b0 3
#335000
1!
10
b0 2
#340000
b1 &
b0 '
b0 #
0!
0/
0-
00
b1 3
#345000
1!
10
b1 2
b10 3
#350000
b0 &
0!
00
#355000
1!
10
b10 2
#360000
b11111111111111111111111111111111 &
0!
00
#365000
1!
10
#370000
0!
00
#375000
1!
10
#380000
b1000010101 %
b11 &
0!
00
#385000
1!
10
#390000
b10 &
b10 '
b10 #
0!
1.
00
b11 3
#395000
1!
10
b11 2
b0 3
#400000
b1 &
b1 '
b1 #
0!
1/
0.
00
#405000
1!
10
b0 2
#410000
b0 &
b101 '
b101 #
0!
1-
00
#415000
1!
10
#420000
b11111111111111111111111111111111 &
0!
00
#425000
1!
10
#430000
0!
00
#435000
1!
10
#440000
b1000101 %
b11 &
b0 '
b0 #
0!
0/
0-
00
b1 3
#445000
1!
10
b1 2
b10 3
#450000
b10 &
0!
00
#455000
1!
10
b10 2
#460000
b1 &
b100 '
b100 #
0!
1-
00
b0 3
#465000
1!
10
b0 2
#470000
b0 &
b101 '
b101 #
0!
1/
00
#475000
1!
10
#480000
b11111111111111111111111111111111 &
0!
00
#485000
1!
10
#490000
0!
00
#495000
1!
10
#500000
b101 %
b11 &
b0 '
b0 #
0!
0/
0-
00
b1 3
#505000
1!
10
b1 2
b10 3
#510000
b10 &
0!
00
#515000
1!
10
b10 2
#520000
b1 &
0!
00
#525000
1!
10
#530000
b0 &
b101 '
b101 #
0!
1/
1-
00
b0 3
#535000
1!
10
b0 2
#540000
b11111111111111111111111111111111 &
0!
00
#545000
1!
10
#550000
0!
00
#555000
1!
10
#560000
b1001101010111 %
b11 &
b1 '
b1 #
0!
0-
00
#565000
1!
10
#570000
b10 &
b11 '
b11 #
0!
1.
00
#575000
1!
10
#580000
b1 &
b101 '
b101 #
0!
0.
1-
00
#585000
1!
10
#590000
b0 &
b111 '
b111 #
0!
1.
00
#595000
1!
10
#600000
b11111111111111111111111111111111 &
0!
00
