Lab3/Lab3_Moore.v
`timescale 1ns/1ps

module Lab3_Moore(CLK, dataIn, RST, odd);
    input [3:0] dataIn;
    input       CLK;
    input       RST;
    output      odd;
    
    // Định nghĩa state là 3-bit để phù hợp với các mã trạng thái
    reg [2:0] state, next_state;
    reg [4:0] sumid, next_sumid;
    
    // Khai báo tham số trạng thái
    parameter RESET = 3'b000;
    parameter S1    = 3'b001;
    parameter S2    = 3'b010;
    parameter S3    = 3'b011;
    parameter S4    = 3'b100;
    
    // Logic tính toán trạng thái và sum tiếp theo (kết hợp)
    always @(*) begin
        // Gán mặc định: giữ nguyên trạng thái và tổng hiện tại
        next_state = state;
        next_sumid = sumid;
        case(state)
            RESET: begin
                if (dataIn == 0) begin
                    next_state = S1;
                    next_sumid = 0;
                end
                else begin
                    next_state = RESET;
                    next_sumid = 0;
                end
            end
            S1: begin
                if (dataIn == 0) begin
                    next_state = S2;
                    next_sumid = 0;
                end
                else begin
                    next_state = RESET;
                    next_sumid = 0;
                end
            end
            S2: begin
                if (dataIn == 2) begin
                    next_state = S3;
                    next_sumid = sumid + 2;
                end
                else if (dataIn == 0) begin
                    next_state = S2; // Giữ nguyên S2, không cập nhật sum
                    next_sumid = sumid;
                end
                else begin
                    next_state = RESET;
                    next_sumid = 0;
                end
            end
            S3: begin
                if (dataIn == 5) begin
                    next_state = S4;
                    next_sumid = sumid + 5;
                end
                else if (dataIn == 0) begin
                    next_state = S1;
                    next_sumid = sumid;
                end
                else begin
                    next_state = RESET;
                    next_sumid = 0;
                end
            end
            S4: begin
                if (dataIn == 0) begin
                    next_state = S1;
                    next_sumid = sumid;
                end
                else begin
                    next_state = RESET;
                    next_sumid = 0;
                end
            end
            default: begin
                next_state = RESET;
                next_sumid = 0;
            end
        endcase
    end

    // Cập nhật các thanh ghi state và sumid theo đồng bộ (có reset đồng bộ)
    always @(posedge CLK or posedge RST) begin
        if (RST) begin
            state <= RESET;
            sumid <= 0;
        end
        else begin
            state <= next_state;
            sumid <= next_sumid;
        end
    end

    // Logic xuất: odd = 1 nếu ở trạng thái S4 và sumid lẻ, ngược lại = 0
    assign odd = ((state == S4) && ((sumid % 2) == 1)) ? 1 : 0;

endmodule

Lab3/Lab3_Moore_tb.v
`timescale 1ns/1ps

module tb_Lab3_Moore;
    reg        CLK;
    reg        RST;
    reg [3:0]  dataIn;
    wire       odd;

    // Instantiate the design under test with named ports
    Lab3_Moore dut (
        .CLK(CLK),
        .dataIn(dataIn),
        .RST(RST),
        .odd(odd)
    );

    // Waveform dump
    initial begin
        $dumpfile("Lab3_Moore_tb.vcd");
        $dumpvars(0, tb_Lab3_Moore);
    end

    // Clock generation: 10 ns period
    initial begin
        CLK = 0;
        forever #5 CLK = ~CLK;
    end

    // Task to drive a sequence of 4 digits.
    // The 16-bit input is structured as {digit0, digit1, digit2, digit3}
    // where digit0 is the first input.
    task drive_sequence;
        input [15:0] seq;
        integer i;
        reg [3:0] digit;
        begin
            // Apply each digit every 10 ns
            for(i = 3; i >= 0; i = i - 1) begin
                // Extract 4 bits per digit using bit slicing.
                digit = seq[(i*4) + 3 -: 4];
                dataIn = digit;
                #10;
            end
        end
    endtask

    initial begin
        // Initialization & reset
        RST = 1;
        dataIn = 4'd0;
        #10;
        RST = 0;
        #10;
        
        // Test Case 1: "0025" (Expected: sum = 0+0+2+5 = 7, odd=1)
        $display("Test Case 1: 0025");
        drive_sequence(16'h0025);
        #20;
        
        // Test Case 2: "1234"
        $display("Test Case 2: 1234");
        drive_sequence(16'h1234);
        #20;
        
        // Test Case 3: "0000"
        $display("Test Case 3: 0000");
        drive_sequence(16'h0000);
        #20;
        
        // Test Case 4: "0020" (Expected: 0+0+2+0 = 2, even => odd=0)
        $display("Test Case 4: 0020");
        drive_sequence(16'h0020);
        #20;
        
        // Test Case 5: "0027" (Sequence fails at last digit; output 0)
        $display("Test Case 5: 0027");
        drive_sequence(16'h0027);
        #20;
        
        // Test Case 6: "0500" (Invalid transition; output 0)
        $display("Test Case 6: 0500");
        drive_sequence(16'h0500);
        #20;
        
        // Test Case 7: "0215" (Invalid sequence; output 0)
        $display("Test Case 7: 0215");
        drive_sequence(16'h0215);
        #20;
        
        // Test Case 8: "0045" (Invalid at s2 transition; output 0)
        $display("Test Case 8: 0045");
        drive_sequence(16'h0045);
        #20;
        
        // Test Case 9: "0005" (Does not complete valid sequence; output 0)
        $display("Test Case 9: 0005");
        drive_sequence(16'h0005);
        #20;
        
        // Test Case 10: "1357" (Random sequence; output depends on FSM transitions)
        $display("Test Case 10: 1357");
        drive_sequence(16'h1357);
        #20;
        
        $finish;
    end

endmodule

Lab3/Lab3_Moore_tb.vcd
$date
	Wed Apr 09 08:11:39 2025
$end
$version
	ModelSim Version 10.1d
$end
$timescale
	1ps
$end
$scope module tb_Lab3_Moore $end
$var reg 1 ! CLK $end
$var reg 1 " RST $end
$var reg 4 # dataIn [3:0] $end
$var wire 1 $ odd $end
$scope task drive_sequence $end
$var reg 16 % seq [15:0] $end
$var integer 32 & i $end
$var reg 4 ' digit [3:0] $end
$upscope $end
$scope module dut $end
$var parameter 3 ( RESET $end
$var parameter 3 ) S1 $end
$var parameter 3 * S2 $end
$var parameter 3 + S3 $end
$var parameter 3 , S4 $end
$var wire 1 - dataIn [3] $end
$var wire 1 . dataIn [2] $end
$var wire 1 / dataIn [1] $end
$var wire 1 0 dataIn [0] $end
$var wire 1 1 CLK $end
$var wire 1 2 RST $end
$var wire 1 $ odd $end
$var reg 3 3 state [2:0] $end
$var reg 3 4 next_state [2:0] $end
$var reg 5 5 sumid [4:0] $end
$var reg 5 6 next_sumid [4:0] $end
$upscope $end
$upscope $end
$enddefinitions $end
#0
$dumpvars
0!
1"
b0 #
b0 3
b1 4
b0 5
b0 6
bx %
bx '
b0 (
b1 )
b10 *
b11 +
b100 ,
bx &
0$
12
00
0/
0.
0-
01
$end
#5000
1!
11
#10000
0"
0!
02
01
#15000
1!
11
b1 3
b10 4
#20000
b100101 %
b11 &
b0 '
0!
01
#25000
1!
11
b10 3
#30000
b10 &
0!
01
#35000
1!
11
#40000
b1 &
b10 '
b10 #
0!
1/
01
b11 4
b10 6
#45000
1!
11
b11 3
b10 5
b0 4
b0 6
#50000
b0 &
b101 '
b101 #
0!
10
0/
1.
01
b11 4
b10 6
b100 4
b111 6
#55000
1!
11
b100 3
b111 5
1$
b0 4
b0 6
#60000
b11111111111111111111111111111111 &
0!
01
#65000
1!
11
b0 3
b0 5
0$
#70000
0!
01
#75000
1!
11
#80000
b1001000110100 %
b11 &
b1 '
b1 #
0!
0.
01
#85000
1!
11
#90000
b10 &
b10 '
b10 #
0!
00
1/
01
#95000
1!
11
#100000
b1 &
b11 '
b11 #
0!
10
01
#105000
1!
11
#110000
b0 &
b100 '
b100 #
0!
00
0/
1.
01
#115000
1!
11
#120000
b11111111111111111111111111111111 &
0!
01
#125000
1!
11
#130000
0!
01
#135000
1!
11
#140000
b0 %
b11 &
b0 '
b0 #
0!
0.
01
b1 4
#145000
1!
11
b1 3
b10 4
#150000
b10 &
0!
01
#155000
1!
11
b10 3
#160000
b1 &
0!
01
#165000
1!
11
#170000
b0 &
0!
01
#175000
1!
11
#180000
b11111111111111111111111111111111 &
0!
01
#185000
1!
11
#190000
0!
01
#195000
1!
11
#200000
b100000 %
b11 &
0!
01
#205000
1!
11
#210000
b10 &
0!
01
#215000
1!
11
#220000
b1 &
b10 '
b10 #
0!
1/
01
b11 4
b10 6
#225000
1!
11
b11 3
b10 5
b0 4
b0 6
#230000
b0 &
b0 '
b0 #
0!
0/
01
b11 4
b10 6
b1 4
#235000
1!
11
b1 3
b10 4
b0 6
#240000
b11111111111111111111111111111111 &
0!
01
#245000
1!
11
b10 3
b0 5
#250000
0!
01
#255000
1!
11
#260000
b100111 %
b11 &
0!
01
#265000
1!
11
#270000
b10 &
0!
01
#275000
1!
11
#280000
b1 &
b10 '
b10 #
0!
1/
01
b11 4
b10 6
#285000
1!
11
b11 3
b10 5
b0 4
b0 6
#290000
b0 &
b111 '
b111 #
0!
10
1.
01
b11 4
b10 6
b0 4
b0 6
#295000
1!
11
b0 3
b0 5
#300000
b11111111111111111111111111111111 &
0!
01
#305000
1!
11
#310000
0!
01
#315000
1!
11
#320000
b10100000000 %
b11 &
b0 '
b0 #
0!
00
0/
0.
01
b1 4
#325000
1!
11
b1 3
b10 4
#330000
b10 &
b101 '
b101 #
0!
10
1.
01
b1 4
b0 4
#335000
1!
11
b0 3
#340000
b1 &
b0 '
b0 #
0!
00
0.
01
b1 4
#345000
1!
11
b1 3
b10 4
#350000
b0 &
0!
01
#355000
1!
11
b10 3
#360000
b11111111111111111111111111111111 &
0!
01
#365000
1!
11
#370000
0!
01
#375000
1!
11
#380000
b1000010101 %
b11 &
0!
01
#385000
1!
11
#390000
b10 &
b10 '
b10 #
0!
1/
01
b11 4
b10 6
#395000
1!
11
b11 3
b10 5
b0 4
b0 6
#400000
b1 &
b1 '
b1 #
0!
10
0/
01
b11 4
b10 6
b0 4
b0 6
#405000
1!
11
b0 3
b0 5
#410000
b0 &
b101 '
b101 #
0!
1.
01
#415000
1!
11
#420000
b11111111111111111111111111111111 &
0!
01
#425000
1!
11
#430000
0!
01
#435000
1!
11
#440000
b1000101 %
b11 &
b0 '
b0 #
0!
00
0.
01
b1 4
#445000
1!
11
b1 3
b10 4
#450000
b10 &
0!
01
#455000
1!
11
b10 3
#460000
b1 &
b100 '
b100 #
0!
1.
01
b0 4
#465000
1!
11
b0 3
#470000
b0 &
b101 '
b101 #
0!
10
01
#475000
1!
11
#480000
b11111111111111111111111111111111 &
0!
01
#485000
1!
11
#490000
0!
01
#495000
1!
11
#500000
b101 %
b11 &
b0 '
b0 #
0!
00
0.
01
b1 4
#505000
1!
11
b1 3
b10 4
#510000
b10 &
0!
01
#515000
1!
11
b10 3
#520000
b1 &
0!
01
#525000
1!
11
#530000
b0 &
b101 '
b101 #
0!
10
1.
01
b0 4
#535000
1!
11
b0 3
#540000
b11111111111111111111111111111111 &
0!
01
#545000
1!
11
#550000
0!
01
#555000
1!
11
#560000
b1001101010111 %
b11 &
b1 '
b1 #
0!
0.
01
#565000
1!
11
#570000
b10 &
b11 '
b11 #
0!
1/
01
#575000
1!
11
#580000
b1 &
b101 '
b101 #
0!
0/
1.
01
#585000
1!
11
#590000
b0 &
b111 '
b111 #
0!
1/
01
#595000
1!
11
#600000
b11111111111111111111111111111111 &
0!
01
